Guess_Who/__init__.py
Guess_Who/envs/__init__.py
Guess_Who/envs/actorcritic.py
Guess_Who/envs/agent.py
Guess_Who/envs/asyncac.py
Guess_Who/envs/character.py
Guess_Who/envs/game.py
Guess_Who/envs/guesswho_env.py
Guess_Who/envs/optimalAgent.py
Guess_Who/envs/player.py
Guess_Who/envs/qnn.py
gym-guesswho/README.txt
gym-guesswho/__init__.py
gym-guesswho/pretrainedAAC
gym-guesswho/pretrainedAC
gym-guesswho/pretrainedACMax
gym-guesswho/pretrainedQNN
gym-guesswho/envs/__init__.py
gym-guesswho/envs/actorcritic.py
gym-guesswho/envs/agent.py
gym-guesswho/envs/asyncac.py
gym-guesswho/envs/character.py
gym-guesswho/envs/characterList.txt
gym-guesswho/envs/game.py
gym-guesswho/envs/guesswho_env.py
gym-guesswho/envs/optimalAgent.py
gym-guesswho/envs/player.py
gym-guesswho/envs/qnn.py
gym_guesswho-0.0.5.dist-info/METADATA
gym_guesswho-0.0.5.dist-info/RECORD
gym_guesswho-0.0.5.dist-info/WHEEL
gym_guesswho-0.0.5.dist-info/top_level.txt
